wifi_qr_terminal/__init__.py
wifi_qr_terminal/__main__.py
wifi_qr_terminal/core.py
wifi_qr_terminal/main.py
wifi_qr_terminal-0.1.3.dist-info/licenses/LICENSE
wifi_qr_terminal-0.1.3.dist-info/METADATA
wifi_qr_terminal-0.1.3.dist-info/WHEEL
wifi_qr_terminal-0.1.3.dist-info/entry_points.txt
wifi_qr_terminal-0.1.3.dist-info/top_level.txt
wifi_qr_terminal-0.1.3.dist-info/RECORD
