Metadata-Version: 2.4
Name: wifi-qr-terminal
Version: 0.1.3
Summary: A terminal-based Wi-Fi credential retriever and QR code generator.
Author-email: Albert Mwasisoba <almwassy@gmail.com>
License: MIT License
Project-URL: Homepage, https://github.com/albizzy/wifi-qr-terminal
Keywords: wifi,qrcode,terminal,cli
Classifier: Programming Language :: Python :: 3
Classifier: License :: OSI Approved :: MIT License
Classifier: Operating System :: OS Independent
Classifier: Environment :: Console
Requires-Python: >=3.7
License-File: LICENSE
Requires-Dist: click
Requires-Dist: rich
Requires-Dist: qrcode[pil]
Dynamic: license-file
